ixlab_sshcore-1.0.0.dist-info/licenses/LICENSE
sshcore/__init__.py
sshcore/backups.py
sshcore/config.py
sshcore/constants.py
sshcore/keys.py
sshcore/metadata.py
sshcore/models.py
sshcore/settings.py
ixlab_sshcore-1.0.0.dist-info/METADATA
ixlab_sshcore-1.0.0.dist-info/WHEEL
ixlab_sshcore-1.0.0.dist-info/top_level.txt
ixlab_sshcore-1.0.0.dist-info/RECORD
