Metadata-Version: 2.4
Name: ixlab-sshcore
Version: 1.0.0
Summary: Core SSH config/tagging engine shared by sshcli and sshui.
Author-email: Iacopo Palazzi <iacopo.palazzi@gmail.com>
License-Expression: MIT
Project-URL: Homepage, https://github.com/iakko/sshcore
Keywords: ssh,config,tags
Requires-Python: >=3.10
License-File: LICENSE
Requires-Dist: typer
Requires-Dist: cryptography>=40
Dynamic: license-file
